fds/__init__.py
fds/sdk/__init__.py
fds/sdk/FactSetPartnerFunds/__init__.py
fds/sdk/FactSetPartnerFunds/api_client.py
fds/sdk/FactSetPartnerFunds/configuration.py
fds/sdk/FactSetPartnerFunds/exceptions.py
fds/sdk/FactSetPartnerFunds/model_utils.py
fds/sdk/FactSetPartnerFunds/rest.py
fds/sdk/FactSetPartnerFunds/api/__init__.py
fds/sdk/FactSetPartnerFunds/api/canadian_mutual_fund_data_from_fundata_api.py
fds/sdk/FactSetPartnerFunds/apis/__init__.py
fds/sdk/FactSetPartnerFunds/model/__init__.py
fds/sdk/FactSetPartnerFunds/model/address.py
fds/sdk/FactSetPartnerFunds/model/asset_allocations_response.py
fds/sdk/FactSetPartnerFunds/model/asset_breakdown.py
fds/sdk/FactSetPartnerFunds/model/asset_response_data.py
fds/sdk/FactSetPartnerFunds/model/distribution.py
fds/sdk/FactSetPartnerFunds/model/distributions_data.py
fds/sdk/FactSetPartnerFunds/model/distributions_response.py
fds/sdk/FactSetPartnerFunds/model/dividend.py
fds/sdk/FactSetPartnerFunds/model/error_object.py
fds/sdk/FactSetPartnerFunds/model/error_response.py
fds/sdk/FactSetPartnerFunds/model/fees.py
fds/sdk/FactSetPartnerFunds/model/fees_response.py
fds/sdk/FactSetPartnerFunds/model/fund_counts.py
fds/sdk/FactSetPartnerFunds/model/fund_serv.py
fds/sdk/FactSetPartnerFunds/model/geo_allocations_response.py
fds/sdk/FactSetPartnerFunds/model/geo_breakdown.py
fds/sdk/FactSetPartnerFunds/model/geo_response_data.py
fds/sdk/FactSetPartnerFunds/model/growth_of10_k.py
fds/sdk/FactSetPartnerFunds/model/growth_of10_ks.py
fds/sdk/FactSetPartnerFunds/model/growth_of_ten_k_response.py
fds/sdk/FactSetPartnerFunds/model/holding.py
fds/sdk/FactSetPartnerFunds/model/holding_response_data.py
fds/sdk/FactSetPartnerFunds/model/holdings_response.py
fds/sdk/FactSetPartnerFunds/model/invalid_id_error_object.py
fds/sdk/FactSetPartnerFunds/model/manager.py
fds/sdk/FactSetPartnerFunds/model/nav.py
fds/sdk/FactSetPartnerFunds/model/performance_rankings.py
fds/sdk/FactSetPartnerFunds/model/performance_rankings_response.py
fds_sdk_factsetpartnerfunds-0.1.0.dist-info/licenses/LICENSE
fds_sdk_factsetpartnerfunds-0.1.0.dist-info/METADATA
fds_sdk_factsetpartnerfunds-0.1.0.dist-info/WHEEL
fds_sdk_factsetpartnerfunds-0.1.0.dist-info/top_level.txt
fds_sdk_factsetpartnerfunds-0.1.0.dist-info/RECORD
